marib/PPS.py
marib/__init__.py
marib/vec.py
marib/na/CubicSpline.py
marib/na/Integration.py
marib/na/Lagrange.py
marib/na/LeastSquare.py
marib/na/Newton.py
marib/na/Test.py
marib/na/__init__.py
marib-0.0.1.dist-info/LICENSE.txt
marib-0.0.1.dist-info/METADATA
marib-0.0.1.dist-info/WHEEL
marib-0.0.1.dist-info/top_level.txt
marib-0.0.1.dist-info/RECORD
