Metadata-Version: 2.1
Name: marib
Version: 0.0.1
Summary: A small package, with something about numerical analysis.
Author: Marisa
Author-email: 
Classifier: Programming Language :: Python :: 3
Classifier: License :: OSI Approved :: MIT License
Classifier: Operating System :: OS Independent
License-File: LICENSE.txt
